<?xml version="1.0" encoding="UTF-8"?>
<?oxygen RNGSchema="shared/cpf.rng" type="xml"?>
<eac-cpf xmlns="urn:isbn:1-931666-33-4" xmlns:xlink="http://www.w3.org/1999/xlink" xmlns:xsi="http://www.w3.org/2001/XMLSchema-instance" xsi:schemaLocation="urn:isbn:1-931666-33-4 http://eac.staatsbibliothek-berlin.de/schema/cpf.xsd">
<control>
<recordId>AWE1119</recordId>
<maintenanceStatus>revised</maintenanceStatus>
<maintenanceAgency>
<agencyCode>AU-VU:AWR</agencyCode>
<agencyName>The  Australian Women's Register</agencyName>
<descriptiveNote>
<p></p>
</descriptiveNote>
</maintenanceAgency>
<languageDeclaration>
<language languageCode="eng">English</language>
<script scriptCode="Latn">Latin</script>
</languageDeclaration>
<conventionDeclaration>
<abbreviation>AACR2</abbreviation>
<citation>Anglo-American Cataloguing Rules</citation>
</conventionDeclaration>
<localControl localType="typeOfEntity">
<term>Corporate Body</term>
</localControl>
<maintenanceHistory>
<maintenanceEvent>
<eventType>created</eventType>
<eventDateTime standardDateTime="2004-12-03">2004-12-03</eventDateTime>
<agentType>human</agentType>
<agent>Rosemary Francis</agent>
<eventDescription></eventDescription>
</maintenanceEvent>
<maintenanceEvent>
<eventType>updated</eventType>
<eventDateTime standardDateTime="2013-09-13">2013-09-13</eventDateTime>
<agentType>human</agentType>
<agent></agent>
<eventDescription></eventDescription>
</maintenanceEvent>
</maintenanceHistory>
</control>
<cpfDescription>
<identity><entityId>http://www.womenaustralia.info/biogs/AWE1119b.htm</entityId>
<entityType>corporateBody</entityType>
<nameEntry><part>SDN Children's Services Inc.</part>
<authorizedForm>AACR2</authorizedForm>
</nameEntry>
<nameEntry localType="former name"><part>Sydney Day Nursery Association</part>
<useDates>
<dateRange>
<fromDate standardDate="1905-01-01">1905</fromDate>
<toDate standardDate="1931-12-31">1931</toDate>
</dateRange>
</useDates>
</nameEntry>
<nameEntry localType="former name"><part>Sydney Day Nursery and Nursery Schools Association Inc.</part>
<useDates>
<dateRange>
<fromDate standardDate="1931-01-01">1931</fromDate>
<toDate standardDate="1999-12-31">1999</toDate>
</dateRange>
</useDates>
</nameEntry>
</identity>
<description><existDates>
<dateRange>
<fromDate standardDate="1905-01-01">1905</fromDate>
</dateRange>
</existDates>
<places>
<place>
<placeRole>Start Place</placeRole>
<placeEntry>Woolloomooloo, New South Wales, Australia</placeEntry>
</place>
<place>
<placeRole>Location</placeRole>
<placeEntry>Level I
141-145 Pitt St
Redfern NSW 2016</placeEntry>
</place>
</places>
<functions>
<function>
<term>Welfare organisation</term>
</function>
</functions>
<biogHist>
<abstract>SDN Children's Services Inc. was the first organisation in Australia to provide all day care for children.The Sydney Day Nursery was established in 1905 in Woolloomooloo on the initiative of a group of young women with an interest in young children's care and education as a result of their involvement in the Sydney Kindergarten Union. The organization aimed to 'preserve family life, to educate mothers in child health and to save babies from death and from becoming State wards'. The Day Nursery catered for infants and toddlers ranging in age from a few weeks to three years. By 1927 the Association had established five centres. It changed its name in 1931 to become the Sydney Day Nursery and Nursery Schools Association Inc. and in 1934 it established the Nursery School Teachers Training College. It changed its name again in 1999 to become SDN Children's Services Inc. This new name reflected an expansion of services for children other than centre based long day care.</abstract>
<p>The women who established the Sydney Day Nursery Association did not want their new organisation to be a 'cold, remote charity, but an institution started by fellow women, who fully realise the difficulties that beset the paths of working mothers'.<br />
Women supported the Nursery financially through the formation of Circles, each of which was required to raise ten pounds a year to maintain a cot in the House.<br />
In addition to increasing the number of centres, the Association established the Nursery School Teachers Training College in 1934 to train teachers to work with children from birth to eight years of age. It ultimately merged with the Sydney Kindergarten Teachers College to become a faculty within the Sydney College of Advanced Education. In 1994 the Institute of Early Childhood Studies became the Institute of Early Childhood located at the Macquarie University Campus.<br />
 Sydney women have continued to work in an honorary capacity as Executive and Board members to maintain and extend the services available to pre-school children with twenty-two centres currently operating.</p>

</biogHist>
</description>
<relations><cpfRelation cpfRelationType="identity" xlink:type="simple" xlink:href="http://nla.gov.au/nla.party-642442">
<relationEntry></relationEntry>
<descriptiveNote><p>Trove</p>
</descriptiveNote>
</cpfRelation>
<resourceRelation resourceRelationType="subjectOf">
<relationEntry localType="published">'SDN Children's Services Inc.', in <span style="font-style:italic">The  Australian Women's Register</span>, National Foundation for Australian Women and The University of Melbourne</relationEntry>

<objectXMLWrap>
<bibref xmlns="urn:isbn:1-931666-22-9">
<title render="italic">SDN Children's Services Inc.</title>
<imprint>
<publisher>National Foundation for Australian Women</publisher>
</imprint>
<bibseries>
<title render="italic">The  Australian Women's Register</title>
</bibseries>
<extptr linktype="simple" href="http://www.womenaustralia.info/biogs/AWE1119b.htm"></extptr>
</bibref>
</objectXMLWrap>
</resourceRelation>
<resourceRelation resourceRelationType="other" xlink:type="simple" xlink:href="http://www.womenaustralia.info/bib/AWP003405.htm">
<relationEntry localType="published">Book: Early childhood play activities / compiled by Christine Richardson in conjunction with staff of Sydney Day Nursery &amp; Nursery Schools Association ( Inc.) : cover illustration, Robyn Hutchison</relationEntry>

<objectXMLWrap>
<bibref xmlns="urn:isbn:1-931666-22-9">
<name type="author"></name>
<title render="italic">Early childhood play activities / compiled by Christine Richardson in conjunction with staff of Sydney Day Nursery &amp; Nursery Schools Association ( Inc.) : cover illustration, Robyn Hutchison</title>
<imprint>
<place>Sydney</place>
<publisher>Sydney Day Nursery and Nursery Schools Association</publisher>
<date>1979</date>
</imprint>
</bibref>
</objectXMLWrap>

</resourceRelation>
<resourceRelation resourceRelationType="other" xlink:type="simple" xlink:href="http://www.womenaustralia.info/bib/AWP003404.htm">
<relationEntry localType="published">Book: Do and learn</relationEntry>

<objectXMLWrap>
<bibref xmlns="urn:isbn:1-931666-22-9">
<name type="author">Cuthbertson, Michelle</name>
<title render="italic">Do and learn</title>
<imprint>
<place>Refern, N.S.W.</place>
<publisher>Sydney Day Nursery and Nursery Schools Association</publisher>
<date>1997</date>
</imprint>
</bibref>
</objectXMLWrap>

</resourceRelation>
<resourceRelation resourceRelationType="creatorOf" xlink:type="simple" xlink:href="http://www.womenaustralia.info/bib/AWP003407.htm">
<relationEntry localType="published">Report: Annual report / Sydney Day Nursery Association</relationEntry>

<objectXMLWrap>
<bibref xmlns="urn:isbn:1-931666-22-9">
<name type="author">Sydney Day Nursery Association</name>
<title render="italic">Annual report / Sydney Day Nursery Association</title>
<imprint>
<place>Sydney</place>
<publisher>The Association</publisher>
<date>1905-1936</date>
</imprint>
</bibref>
</objectXMLWrap>

</resourceRelation>
<resourceRelation resourceRelationType="creatorOf" xlink:type="simple" xlink:href="http://www.womenaustralia.info/bib/AWP003406.htm">
<relationEntry localType="published">Report: Annual report / The Sydney Day Nursery and Nursery Schools Association</relationEntry>

<objectXMLWrap>
<bibref xmlns="urn:isbn:1-931666-22-9">
<name type="author">Sydney Day Nursery and Nursery Schools Association</name>
<title render="italic">Annual report / The Sydney Day Nursery and Nursery Schools Association</title>
<imprint>
<place>Sydney</place>
<publisher>The Association</publisher>
<date>1936/37-1998</date>
</imprint>
</bibref>
</objectXMLWrap>

</resourceRelation>
<resourceRelation resourceRelationType="creatorOf" xlink:type="simple" xlink:href="http://www.womenaustralia.info/archives/AWH001890.htm">
<relationEntry localType="archival">SDN Children's Services Inc. - records, 1908-1993</relationEntry>

<objectXMLWrap>
<archref xmlns="urn:isbn:1-931666-22-9">
<repository>Mitchell and Dixson Libraries Manuscripts Collection, State Library of New South Wales</repository>
<unittitle>SDN Children's Services Inc. - records, 1908-1993</unittitle>
<unitid>MLMSS</unitid>
<unitdate>1908 - 1993</unitdate>
<abstract>This collection comprises the records of the Sydney Day Nursery. It includes minutes of the executive committee, special and general meetings and the nursery school subcommittee, and the register of subscriptions and donations.</abstract>
<physdesc>
<extent>6 boxes</extent>
<physfacet>Minutes</physfacet>
</physdesc>
</archref>
</objectXMLWrap>

</resourceRelation>
</relations>
</cpfDescription>
</eac-cpf>