<?xml version="1.0" encoding="UTF-8"?>
<?oxygen RNGSchema="shared/cpf.rng" type="xml"?>
<eac-cpf xmlns="urn:isbn:1-931666-33-4" xmlns:xlink="http://www.w3.org/1999/xlink" xmlns:xsi="http://www.w3.org/2001/XMLSchema-instance" xsi:schemaLocation="urn:isbn:1-931666-33-4 http://eac.staatsbibliothek-berlin.de/schema/cpf.xsd">
<control>
<recordId>AWE4053</recordId>
<maintenanceStatus>revised</maintenanceStatus>
<maintenanceAgency>
<agencyCode>AU-VU:AWR</agencyCode>
<agencyName>The  Australian Women's Register</agencyName>
<descriptiveNote>
<p></p>
</descriptiveNote>
</maintenanceAgency>
<languageDeclaration>
<language languageCode="eng">English</language>
<script scriptCode="Latn">Latin</script>
</languageDeclaration>
<conventionDeclaration>
<abbreviation>AACR2</abbreviation>
<citation>Anglo-American Cataloguing Rules</citation>
</conventionDeclaration>
<localControl localType="typeOfEntity">
<term>Person</term>
</localControl>
<maintenanceHistory>
<maintenanceEvent>
<eventType>created</eventType>
<eventDateTime standardDateTime="2009-02-12">2009-02-12</eventDateTime>
<agentType>human</agentType>
<agent>Barbara Lemon</agent>
<eventDescription></eventDescription>
</maintenanceEvent>
<maintenanceEvent>
<eventType>updated</eventType>
<eventDateTime standardDateTime="2013-09-13">2013-09-13</eventDateTime>
<agentType>human</agentType>
<agent></agent>
<eventDescription></eventDescription>
</maintenanceEvent>
</maintenanceHistory>
</control>
<cpfDescription>
<identity><entityId>http://www.womenaustralia.info/biogs/AWE4053b.htm</entityId>
<entityType>person</entityType>
<nameEntry><part localType="familyname">Kernot</part>
<part localType="givenname">Rhoda Joan</part>
<authorizedForm>AACR2</authorizedForm>
</nameEntry>
</identity>
<description><existDates>
<dateRange>
<fromDate standardDate="1899-03-29">29 March 1899</fromDate>
<toDate standardDate="1978-08-08">8 August 1978</toDate>
</dateRange>
</existDates>
<places>
<place>
<placeRole>Place of Birth</placeRole>
<placeEntry>Magill, South Australia</placeEntry>
</place>
<place>
<placeRole>Place of Death</placeRole>
<placeEntry>Broken Hill, New South Wales, Australia</placeEntry>
</place>
</places>
<occupations>
<occupation>
<term>Nurse</term>
</occupation>
</occupations>
<biogHist>
<abstract>Rhoda Kernot opened the La Balfour hospital in Broken Hill, New South Wales, in 1924.</abstract>
<p>Rhoda Kernot was the daughter of Ellis Edwin Kernot and Christina Mary Ann Mackay. Ellis Edwin was the son of Edwin Wight Kernot and Joan Matthews. Joan was the daughter of Thomas Matthews, who sailed from Pitney, Somerset Shire, on the <span style="font-style:italic">Moffatt</span> and arrived in South Australia in December 1839. Rhoda's siblings were William Charles Kernot and Mary Ruby Smythe Kernot.</p>
<p>Rhoda Kernot attended the Central Public School in Broken Hill and worked at Torpy's Boot Emporium in Argent Street. She was a promising pianist but had to have the first finger of her right hand amputated after an accident during a fierce storm, and she began training as a nurse. She worked at the Broken Hill District Hospital between 1918 and 1921, when she moved to Adelaide, but she returned in 1924 to open her own hospital, La Balfour, on the corner of Williams and Oxide Streets. She moved the hospital to 190 Wills Street in 1926, but fell on hard times during the depression years and began working for doctors in town including Dr. William MacGillivray, Dr. Ian MacGillivray, and Dr. Franziska Schlink.</p>
<p>Rhoda Kernot married Henry Boyd Clark, himself the son of grazier Thomas Clark and his wife Jane Elizabeth Ford. Henry and Rhoda had two children: Patricia Margaret and Edwin Wight Boyd Clark. A family tree is held at the Outback Archives, Broken Hill, and materials belonging to Rhoda including photographs and medical instruments are held by the Broken Hill Railway Museum.</p>

</biogHist>
</description>
<relations><cpfRelation cpfRelationType="identity" xlink:type="simple" xlink:href="http://nla.gov.au/nla.party-722055">
<relationEntry>
Kernot, Rhoda Joan (1899-1978)
</relationEntry>
<descriptiveNote><p>Trove</p>
</descriptiveNote>
</cpfRelation>
<resourceRelation resourceRelationType="subjectOf">
<relationEntry localType="published">'Kernot, Rhoda Joan', in <span style="font-style:italic">The  Australian Women's Register</span>, National Foundation for Australian Women and The University of Melbourne</relationEntry>

<objectXMLWrap>
<bibref xmlns="urn:isbn:1-931666-22-9">
<title render="italic">Kernot, Rhoda Joan</title>
<imprint>
<publisher>National Foundation for Australian Women</publisher>
</imprint>
<bibseries>
<title render="italic">The  Australian Women's Register</title>
</bibseries>
<extptr linktype="simple" href="http://www.womenaustralia.info/biogs/AWE4053b.htm"></extptr>
</bibref>
</objectXMLWrap>
</resourceRelation>
<resourceRelation resourceRelationType="other" xlink:type="simple" xlink:href="http://www.womenaustralia.info/bib/AWP004564.htm">
<relationEntry localType="published">Site Exhibition: Unbroken Spirit: Women in Broken Hill</relationEntry>

<objectXMLWrap>
<bibref xmlns="urn:isbn:1-931666-22-9">
<name type="author">Australian Women's Archives Project</name>
<title render="italic">Unbroken Spirit: Women in Broken Hill</title>
<imprint>
<publisher>Australian Women's Archives Project</publisher>
<date>2009</date>
</imprint>
<extptr linktype="simple" href="http://www.womenaustralia.info/exhib/bh/bh-home.html"></extptr>
</bibref>
</objectXMLWrap>

</resourceRelation>
<resourceRelation resourceRelationType="subjectOf" xlink:type="simple" xlink:href="http://www.womenaustralia.info/archives/AWH002187.htm">
<relationEntry localType="archival">Kernot, Rhoda</relationEntry>

<objectXMLWrap>
<archref xmlns="urn:isbn:1-931666-22-9">
<repository>Outback Archives, Broken Hill City Library</repository>
<unittitle>Kernot, Rhoda</unittitle>
<unitid>Filing system by name</unitid>
<abstract>Folder containing family tree and notes.</abstract>
<physdesc>
<extent></extent>
<physfacet>Typescript</physfacet>
</physdesc>
</archref>
</objectXMLWrap>

<descriptiveNote>
<p>Source used to compile entry</p>
</descriptiveNote>
</resourceRelation>
</relations>
</cpfDescription>
</eac-cpf>